[{"unicode":"U+13162","char":"𓅢","name":"EGYPTIAN HIEROGLYPH G030","category":"ancient_scripts","block":"Egyptian Hieroglyphs","required_font_family":"NotoSansEgyptianHieroglyphs-Regular"},{"unicode":"U+13163","char":"𓅣","name":"EGYPTIAN HIEROGLYPH G031","category":"ancient_scripts","block":"Egyptian Hieroglyphs","required_font_family":"NotoSansEgyptianHieroglyphs-Regular"},{"unicode":"U+13164","char":"𓅤","name":"EGYPTIAN HIEROGLYPH G032","category":"ancient_scripts","block":"Egyptian Hieroglyphs","required_font_family":"NotoSansEgyptianHieroglyphs-Regular"},{"unicode":"U+13165","char":"𓅥","name":"EGYPTIAN HIEROGLYPH G033","category":"ancient_scripts","block":"Egyptian Hieroglyphs","required_font_family":"NotoSansEgyptianHieroglyphs-Regular"},{"unicode":"U+13166","char":"𓅦","name":"EGYPTIAN HIEROGLYPH G034","category":"ancient_scripts","block":"Egyptian Hieroglyphs","required_font_family":"NotoSansEgyptianHieroglyphs-Regular"},{"unicode":"U+13167","char":"𓅧","name":"EGYPTIAN HIEROGLYPH G035","category":"ancient_scripts","block":"Egyptian Hieroglyphs","required_font_family":"NotoSansEgyptianHieroglyphs-Regular"},{"unicode":"U+13168","char":"𓅨","name":"EGYPTIAN HIEROGLYPH G036","category":"ancient_scripts","block":"Egyptian Hieroglyphs","required_font_family":"NotoSansEgyptianHieroglyphs-Regular"},{"unicode":"U+13169","char":"𓅩","name":"EGYPTIAN HIEROGLYPH G036A","category":"ancient_scripts","block":"Egyptian Hieroglyphs","required_font_family":"NotoSansEgyptianHieroglyphs-Regular"},{"unicode":"U+1316A","char":"𓅪","name":"EGYPTIAN HIEROGLYPH G037","category":"ancient_scripts","block":"Egyptian Hieroglyphs","required_font_family":"NotoSansEgyptianHieroglyphs-Regular"},{"unicode":"U+1316B","char":"𓅫","name":"EGYPTIAN HIEROGLYPH G037A","category":"ancient_scripts","block":"Egyptian Hieroglyphs","required_font_family":"NotoSansEgyptianHieroglyphs-Regular"},{"unicode":"U+1316C","char":"𓅬","name":"EGYPTIAN HIEROGLYPH G038","category":"ancient_scripts","block":"Egyptian Hieroglyphs","required_font_family":"NotoSansEgyptianHieroglyphs-Regular"},{"unicode":"U+1316D","char":"𓅭","name":"EGYPTIAN HIEROGLYPH G039","category":"ancient_scripts","block":"Egyptian Hieroglyphs","required_font_family":"NotoSansEgyptianHieroglyphs-Regular"},{"unicode":"U+1316E","char":"𓅮","name":"EGYPTIAN HIEROGLYPH G040","category":"ancient_scripts","block":"Egyptian Hieroglyphs","required_font_family":"NotoSansEgyptianHieroglyphs-Regular"},{"unicode":"U+1316F","char":"𓅯","name":"EGYPTIAN HIEROGLYPH G041","category":"ancient_scripts","block":"Egyptian Hieroglyphs","required_font_family":"NotoSansEgyptianHieroglyphs-Regular"},{"unicode":"U+13170","char":"𓅰","name":"EGYPTIAN HIEROGLYPH G042","category":"ancient_scripts","block":"Egyptian Hieroglyphs","required_font_family":"NotoSansEgyptianHieroglyphs-Regular"},{"unicode":"U+13171","char":"𓅱","name":"EGYPTIAN HIEROGLYPH G043","category":"ancient_scripts","block":"Egyptian Hieroglyphs","required_font_family":"NotoSansEgyptianHieroglyphs-Regular"},{"unicode":"U+13172","char":"𓅲","name":"EGYPTIAN HIEROGLYPH G043A","category":"ancient_scripts","block":"Egyptian Hieroglyphs","required_font_family":"NotoSansEgyptianHieroglyphs-Regular"},{"unicode":"U+13173","char":"𓅳","name":"EGYPTIAN HIEROGLYPH G044","category":"ancient_scripts","block":"Egyptian Hieroglyphs","required_font_family":"NotoSansEgyptianHieroglyphs-Regular"},{"unicode":"U+13174","char":"𓅴","name":"EGYPTIAN HIEROGLYPH G045","category":"ancient_scripts","block":"Egyptian Hieroglyphs","required_font_family":"NotoSansEgyptianHieroglyphs-Regular"},{"unicode":"U+13175","char":"𓅵","name":"EGYPTIAN HIEROGLYPH G045A","category":"ancient_scripts","block":"Egyptian Hieroglyphs","required_font_family":"NotoSansEgyptianHieroglyphs-Regular"},{"unicode":"U+13176","char":"𓅶","name":"EGYPTIAN HIEROGLYPH G046","category":"ancient_scripts","block":"Egyptian Hieroglyphs","required_font_family":"NotoSansEgyptianHieroglyphs-Regular"},{"unicode":"U+13177","char":"𓅷","name":"EGYPTIAN HIEROGLYPH G047","category":"ancient_scripts","block":"Egyptian Hieroglyphs","required_font_family":"NotoSansEgyptianHieroglyphs-Regular"},{"unicode":"U+13178","char":"𓅸","name":"EGYPTIAN HIEROGLYPH G048","category":"ancient_scripts","block":"Egyptian Hieroglyphs","required_font_family":"NotoSansEgyptianHieroglyphs-Regular"},{"unicode":"U+13179","char":"𓅹","name":"EGYPTIAN HIEROGLYPH G049","category":"ancient_scripts","block":"Egyptian Hieroglyphs","required_font_family":"NotoSansEgyptianHieroglyphs-Regular"},{"unicode":"U+1317A","char":"𓅺","name":"EGYPTIAN HIEROGLYPH G050","category":"ancient_scripts","block":"Egyptian Hieroglyphs","required_font_family":"NotoSansEgyptianHieroglyphs-Regular"},{"unicode":"U+1317B","char":"𓅻","name":"EGYPTIAN HIEROGLYPH G051","category":"ancient_scripts","block":"Egyptian Hieroglyphs","required_font_family":"NotoSansEgyptianHieroglyphs-Regular"},{"unicode":"U+1317C","char":"𓅼","name":"EGYPTIAN HIEROGLYPH G052","category":"ancient_scripts","block":"Egyptian Hieroglyphs","required_font_family":"NotoSansEgyptianHieroglyphs-Regular"},{"unicode":"U+1317D","char":"𓅽","name":"EGYPTIAN HIEROGLYPH G053","category":"ancient_scripts","block":"Egyptian Hieroglyphs","required_font_family":"NotoSansEgyptianHieroglyphs-Regular"},{"unicode":"U+1317E","char":"𓅾","name":"EGYPTIAN HIEROGLYPH G054","category":"ancient_scripts","block":"Egyptian Hieroglyphs","required_font_family":"NotoSansEgyptianHieroglyphs-Regular"},{"unicode":"U+1317F","char":"𓅿","name":"EGYPTIAN HIEROGLYPH H001","category":"ancient_scripts","block":"Egyptian Hieroglyphs","required_font_family":"NotoSansEgyptianHieroglyphs-Regular"},{"unicode":"U+13180","char":"𓆀","name":"EGYPTIAN HIEROGLYPH H002","category":"ancient_scripts","block":"Egyptian Hieroglyphs","required_font_family":"NotoSansEgyptianHieroglyphs-Regular"},{"unicode":"U+13181","char":"𓆁","name":"EGYPTIAN HIEROGLYPH H003","category":"ancient_scripts","block":"Egyptian Hieroglyphs","required_font_family":"NotoSansEgyptianHieroglyphs-Regular"},{"unicode":"U+13182","char":"𓆂","name":"EGYPTIAN HIEROGLYPH H004","category":"ancient_scripts","block":"Egyptian Hieroglyphs","required_font_family":"NotoSansEgyptianHieroglyphs-Regular"},{"unicode":"U+13183","char":"𓆃","name":"EGYPTIAN HIEROGLYPH H005","category":"ancient_scripts","block":"Egyptian Hieroglyphs","required_font_family":"NotoSansEgyptianHieroglyphs-Regular"},{"unicode":"U+13184","char":"𓆄","name":"EGYPTIAN HIEROGLYPH H006","category":"ancient_scripts","block":"Egyptian Hieroglyphs","required_font_family":"NotoSansEgyptianHieroglyphs-Regular"},{"unicode":"U+13185","char":"𓆅","name":"EGYPTIAN HIEROGLYPH H006A","category":"ancient_scripts","block":"Egyptian Hieroglyphs","required_font_family":"NotoSansEgyptianHieroglyphs-Regular"},{"unicode":"U+13186","char":"𓆆","name":"EGYPTIAN HIEROGLYPH H007","category":"ancient_scripts","block":"Egyptian Hieroglyphs","required_font_family":"NotoSansEgyptianHieroglyphs-Regular"},{"unicode":"U+13187","char":"𓆇","name":"EGYPTIAN HIEROGLYPH H008","category":"ancient_scripts","block":"Egyptian Hieroglyphs","required_font_family":"NotoSansEgyptianHieroglyphs-Regular"},{"unicode":"U+13188","char":"𓆈","name":"EGYPTIAN HIEROGLYPH I001","category":"ancient_scripts","block":"Egyptian Hieroglyphs","required_font_family":"NotoSansEgyptianHieroglyphs-Regular"},{"unicode":"U+13189","char":"𓆉","name":"EGYPTIAN HIEROGLYPH I002","category":"ancient_scripts","block":"Egyptian Hieroglyphs","required_font_family":"NotoSansEgyptianHieroglyphs-Regular"},{"unicode":"U+1318A","char":"𓆊","name":"EGYPTIAN HIEROGLYPH I003","category":"ancient_scripts","block":"Egyptian Hieroglyphs","required_font_family":"NotoSansEgyptianHieroglyphs-Regular"},{"unicode":"U+1318B","char":"𓆋","name":"EGYPTIAN HIEROGLYPH I004","category":"ancient_scripts","block":"Egyptian Hieroglyphs","required_font_family":"NotoSansEgyptianHieroglyphs-Regular"},{"unicode":"U+1318C","char":"𓆌","name":"EGYPTIAN HIEROGLYPH I005","category":"ancient_scripts","block":"Egyptian Hieroglyphs","required_font_family":"NotoSansEgyptianHieroglyphs-Regular"},{"unicode":"U+1318D","char":"𓆍","name":"EGYPTIAN HIEROGLYPH I005A","category":"ancient_scripts","block":"Egyptian Hieroglyphs","required_font_family":"NotoSansEgyptianHieroglyphs-Regular"},{"unicode":"U+1318E","char":"𓆎","name":"EGYPTIAN HIEROGLYPH I006","category":"ancient_scripts","block":"Egyptian Hieroglyphs","required_font_family":"NotoSansEgyptianHieroglyphs-Regular"},{"unicode":"U+1318F","char":"𓆏","name":"EGYPTIAN HIEROGLYPH I007","category":"ancient_scripts","block":"Egyptian Hieroglyphs","required_font_family":"NotoSansEgyptianHieroglyphs-Regular"},{"unicode":"U+13190","char":"𓆐","name":"EGYPTIAN HIEROGLYPH I008","category":"ancient_scripts","block":"Egyptian Hieroglyphs","required_font_family":"NotoSansEgyptianHieroglyphs-Regular"},{"unicode":"U+13191","char":"𓆑","name":"EGYPTIAN HIEROGLYPH I009","category":"ancient_scripts","block":"Egyptian Hieroglyphs","required_font_family":"NotoSansEgyptianHieroglyphs-Regular"},{"unicode":"U+13192","char":"𓆒","name":"EGYPTIAN HIEROGLYPH I009A","category":"ancient_scripts","block":"Egyptian Hieroglyphs","required_font_family":"NotoSansEgyptianHieroglyphs-Regular"},{"unicode":"U+13193","char":"𓆓","name":"EGYPTIAN HIEROGLYPH I010","category":"ancient_scripts","block":"Egyptian Hieroglyphs","required_font_family":"NotoSansEgyptianHieroglyphs-Regular"},{"unicode":"U+13194","char":"𓆔","name":"EGYPTIAN HIEROGLYPH I010A","category":"ancient_scripts","block":"Egyptian Hieroglyphs","required_font_family":"NotoSansEgyptianHieroglyphs-Regular"},{"unicode":"U+13195","char":"𓆕","name":"EGYPTIAN HIEROGLYPH I011","category":"ancient_scripts","block":"Egyptian Hieroglyphs","required_font_family":"NotoSansEgyptianHieroglyphs-Regular"},{"unicode":"U+13196","char":"𓆖","name":"EGYPTIAN HIEROGLYPH I011A","category":"ancient_scripts","block":"Egyptian Hieroglyphs","required_font_family":"NotoSansEgyptianHieroglyphs-Regular"},{"unicode":"U+13197","char":"𓆗","name":"EGYPTIAN HIEROGLYPH I012","category":"ancient_scripts","block":"Egyptian Hieroglyphs","required_font_family":"NotoSansEgyptianHieroglyphs-Regular"},{"unicode":"U+13198","char":"𓆘","name":"EGYPTIAN HIEROGLYPH I013","category":"ancient_scripts","block":"Egyptian Hieroglyphs","required_font_family":"NotoSansEgyptianHieroglyphs-Regular"},{"unicode":"U+13199","char":"𓆙","name":"EGYPTIAN HIEROGLYPH I014","category":"ancient_scripts","block":"Egyptian Hieroglyphs","required_font_family":"NotoSansEgyptianHieroglyphs-Regular"},{"unicode":"U+1319A","char":"𓆚","name":"EGYPTIAN HIEROGLYPH I015","category":"ancient_scripts","block":"Egyptian Hieroglyphs","required_font_family":"NotoSansEgyptianHieroglyphs-Regular"},{"unicode":"U+1319B","char":"𓆛","name":"EGYPTIAN HIEROGLYPH K001","category":"ancient_scripts","block":"Egyptian Hieroglyphs","required_font_family":"NotoSansEgyptianHieroglyphs-Regular"},{"unicode":"U+1319C","char":"𓆜","name":"EGYPTIAN HIEROGLYPH K002","category":"ancient_scripts","block":"Egyptian Hieroglyphs","required_font_family":"NotoSansEgyptianHieroglyphs-Regular"},{"unicode":"U+1319D","char":"𓆝","name":"EGYPTIAN HIEROGLYPH K003","category":"ancient_scripts","block":"Egyptian Hieroglyphs","required_font_family":"NotoSansEgyptianHieroglyphs-Regular"}]