[{"unicode":"U+144B6","char":"𔒶","name":"ANATOLIAN HIEROGLYPH A155","category":"ancient_scripts","block":"Anatolian Hieroglyphs","required_font_family":"NotoSansAnatolianHieroglyphs-Regular"},{"unicode":"U+144B7","char":"𔒷","name":"ANATOLIAN HIEROGLYPH A156","category":"ancient_scripts","block":"Anatolian Hieroglyphs","required_font_family":"NotoSansAnatolianHieroglyphs-Regular"},{"unicode":"U+144B8","char":"𔒸","name":"ANATOLIAN HIEROGLYPH A157","category":"ancient_scripts","block":"Anatolian Hieroglyphs","required_font_family":"NotoSansAnatolianHieroglyphs-Regular"},{"unicode":"U+144B9","char":"𔒹","name":"ANATOLIAN HIEROGLYPH A158","category":"ancient_scripts","block":"Anatolian Hieroglyphs","required_font_family":"NotoSansAnatolianHieroglyphs-Regular"},{"unicode":"U+144BA","char":"𔒺","name":"ANATOLIAN HIEROGLYPH A159","category":"ancient_scripts","block":"Anatolian Hieroglyphs","required_font_family":"NotoSansAnatolianHieroglyphs-Regular"},{"unicode":"U+144BB","char":"𔒻","name":"ANATOLIAN HIEROGLYPH A160","category":"ancient_scripts","block":"Anatolian Hieroglyphs","required_font_family":"NotoSansAnatolianHieroglyphs-Regular"},{"unicode":"U+144BC","char":"𔒼","name":"ANATOLIAN HIEROGLYPH A161","category":"ancient_scripts","block":"Anatolian Hieroglyphs","required_font_family":"NotoSansAnatolianHieroglyphs-Regular"},{"unicode":"U+144BD","char":"𔒽","name":"ANATOLIAN HIEROGLYPH A162","category":"ancient_scripts","block":"Anatolian Hieroglyphs","required_font_family":"NotoSansAnatolianHieroglyphs-Regular"},{"unicode":"U+144BE","char":"𔒾","name":"ANATOLIAN HIEROGLYPH A163","category":"ancient_scripts","block":"Anatolian Hieroglyphs","required_font_family":"NotoSansAnatolianHieroglyphs-Regular"},{"unicode":"U+144BF","char":"𔒿","name":"ANATOLIAN HIEROGLYPH A164","category":"ancient_scripts","block":"Anatolian Hieroglyphs","required_font_family":"NotoSansAnatolianHieroglyphs-Regular"},{"unicode":"U+144C0","char":"𔓀","name":"ANATOLIAN HIEROGLYPH A165","category":"ancient_scripts","block":"Anatolian Hieroglyphs","required_font_family":"NotoSansAnatolianHieroglyphs-Regular"},{"unicode":"U+144C1","char":"𔓁","name":"ANATOLIAN HIEROGLYPH A166","category":"ancient_scripts","block":"Anatolian Hieroglyphs","required_font_family":"NotoSansAnatolianHieroglyphs-Regular"},{"unicode":"U+144C2","char":"𔓂","name":"ANATOLIAN HIEROGLYPH A167","category":"ancient_scripts","block":"Anatolian Hieroglyphs","required_font_family":"NotoSansAnatolianHieroglyphs-Regular"},{"unicode":"U+144C3","char":"𔓃","name":"ANATOLIAN HIEROGLYPH A168","category":"ancient_scripts","block":"Anatolian Hieroglyphs","required_font_family":"NotoSansAnatolianHieroglyphs-Regular"},{"unicode":"U+144C4","char":"𔓄","name":"ANATOLIAN HIEROGLYPH A169","category":"ancient_scripts","block":"Anatolian Hieroglyphs","required_font_family":"NotoSansAnatolianHieroglyphs-Regular"},{"unicode":"U+144C5","char":"𔓅","name":"ANATOLIAN HIEROGLYPH A170","category":"ancient_scripts","block":"Anatolian Hieroglyphs","required_font_family":"NotoSansAnatolianHieroglyphs-Regular"},{"unicode":"U+144C6","char":"𔓆","name":"ANATOLIAN HIEROGLYPH A171","category":"ancient_scripts","block":"Anatolian Hieroglyphs","required_font_family":"NotoSansAnatolianHieroglyphs-Regular"},{"unicode":"U+144C7","char":"𔓇","name":"ANATOLIAN HIEROGLYPH A172","category":"ancient_scripts","block":"Anatolian Hieroglyphs","required_font_family":"NotoSansAnatolianHieroglyphs-Regular"},{"unicode":"U+144C8","char":"𔓈","name":"ANATOLIAN HIEROGLYPH A173","category":"ancient_scripts","block":"Anatolian Hieroglyphs","required_font_family":"NotoSansAnatolianHieroglyphs-Regular"},{"unicode":"U+144C9","char":"𔓉","name":"ANATOLIAN HIEROGLYPH A174","category":"ancient_scripts","block":"Anatolian Hieroglyphs","required_font_family":"NotoSansAnatolianHieroglyphs-Regular"},{"unicode":"U+144CA","char":"𔓊","name":"ANATOLIAN HIEROGLYPH A175","category":"ancient_scripts","block":"Anatolian Hieroglyphs","required_font_family":"NotoSansAnatolianHieroglyphs-Regular"},{"unicode":"U+144CB","char":"𔓋","name":"ANATOLIAN HIEROGLYPH A176","category":"ancient_scripts","block":"Anatolian Hieroglyphs","required_font_family":"NotoSansAnatolianHieroglyphs-Regular"},{"unicode":"U+144CC","char":"𔓌","name":"ANATOLIAN HIEROGLYPH A177","category":"ancient_scripts","block":"Anatolian Hieroglyphs","required_font_family":"NotoSansAnatolianHieroglyphs-Regular"},{"unicode":"U+144CD","char":"𔓍","name":"ANATOLIAN HIEROGLYPH A178","category":"ancient_scripts","block":"Anatolian Hieroglyphs","required_font_family":"NotoSansAnatolianHieroglyphs-Regular"},{"unicode":"U+144CE","char":"𔓎","name":"ANATOLIAN HIEROGLYPH A179","category":"ancient_scripts","block":"Anatolian Hieroglyphs","required_font_family":"NotoSansAnatolianHieroglyphs-Regular"},{"unicode":"U+144CF","char":"𔓏","name":"ANATOLIAN HIEROGLYPH A180","category":"ancient_scripts","block":"Anatolian Hieroglyphs","required_font_family":"NotoSansAnatolianHieroglyphs-Regular"},{"unicode":"U+144D0","char":"𔓐","name":"ANATOLIAN HIEROGLYPH A181","category":"ancient_scripts","block":"Anatolian Hieroglyphs","required_font_family":"NotoSansAnatolianHieroglyphs-Regular"},{"unicode":"U+144D1","char":"𔓑","name":"ANATOLIAN HIEROGLYPH A182","category":"ancient_scripts","block":"Anatolian Hieroglyphs","required_font_family":"NotoSansAnatolianHieroglyphs-Regular"},{"unicode":"U+144D2","char":"𔓒","name":"ANATOLIAN HIEROGLYPH A183","category":"ancient_scripts","block":"Anatolian Hieroglyphs","required_font_family":"NotoSansAnatolianHieroglyphs-Regular"},{"unicode":"U+144D3","char":"𔓓","name":"ANATOLIAN HIEROGLYPH A184","category":"ancient_scripts","block":"Anatolian Hieroglyphs","required_font_family":"NotoSansAnatolianHieroglyphs-Regular"},{"unicode":"U+144D4","char":"𔓔","name":"ANATOLIAN HIEROGLYPH A185","category":"ancient_scripts","block":"Anatolian Hieroglyphs","required_font_family":"NotoSansAnatolianHieroglyphs-Regular"},{"unicode":"U+144D5","char":"𔓕","name":"ANATOLIAN HIEROGLYPH A186","category":"ancient_scripts","block":"Anatolian Hieroglyphs","required_font_family":"NotoSansAnatolianHieroglyphs-Regular"},{"unicode":"U+144D6","char":"𔓖","name":"ANATOLIAN HIEROGLYPH A187","category":"ancient_scripts","block":"Anatolian Hieroglyphs","required_font_family":"NotoSansAnatolianHieroglyphs-Regular"},{"unicode":"U+144D7","char":"𔓗","name":"ANATOLIAN HIEROGLYPH A188","category":"ancient_scripts","block":"Anatolian Hieroglyphs","required_font_family":"NotoSansAnatolianHieroglyphs-Regular"},{"unicode":"U+144D8","char":"𔓘","name":"ANATOLIAN HIEROGLYPH A189","category":"ancient_scripts","block":"Anatolian Hieroglyphs","required_font_family":"NotoSansAnatolianHieroglyphs-Regular"},{"unicode":"U+144D9","char":"𔓙","name":"ANATOLIAN HIEROGLYPH A190","category":"ancient_scripts","block":"Anatolian Hieroglyphs","required_font_family":"NotoSansAnatolianHieroglyphs-Regular"},{"unicode":"U+144DA","char":"𔓚","name":"ANATOLIAN HIEROGLYPH A191","category":"ancient_scripts","block":"Anatolian Hieroglyphs","required_font_family":"NotoSansAnatolianHieroglyphs-Regular"},{"unicode":"U+144DB","char":"𔓛","name":"ANATOLIAN HIEROGLYPH A192","category":"ancient_scripts","block":"Anatolian Hieroglyphs","required_font_family":"NotoSansAnatolianHieroglyphs-Regular"},{"unicode":"U+144DC","char":"𔓜","name":"ANATOLIAN HIEROGLYPH A193","category":"ancient_scripts","block":"Anatolian Hieroglyphs","required_font_family":"NotoSansAnatolianHieroglyphs-Regular"},{"unicode":"U+144DD","char":"𔓝","name":"ANATOLIAN HIEROGLYPH A194","category":"ancient_scripts","block":"Anatolian Hieroglyphs","required_font_family":"NotoSansAnatolianHieroglyphs-Regular"},{"unicode":"U+144DE","char":"𔓞","name":"ANATOLIAN HIEROGLYPH A195","category":"ancient_scripts","block":"Anatolian Hieroglyphs","required_font_family":"NotoSansAnatolianHieroglyphs-Regular"},{"unicode":"U+144DF","char":"𔓟","name":"ANATOLIAN HIEROGLYPH A196","category":"ancient_scripts","block":"Anatolian Hieroglyphs","required_font_family":"NotoSansAnatolianHieroglyphs-Regular"},{"unicode":"U+144E0","char":"𔓠","name":"ANATOLIAN HIEROGLYPH A197","category":"ancient_scripts","block":"Anatolian Hieroglyphs","required_font_family":"NotoSansAnatolianHieroglyphs-Regular"},{"unicode":"U+144E1","char":"𔓡","name":"ANATOLIAN HIEROGLYPH A198","category":"ancient_scripts","block":"Anatolian Hieroglyphs","required_font_family":"NotoSansAnatolianHieroglyphs-Regular"},{"unicode":"U+144E2","char":"𔓢","name":"ANATOLIAN HIEROGLYPH A199","category":"ancient_scripts","block":"Anatolian Hieroglyphs","required_font_family":"NotoSansAnatolianHieroglyphs-Regular"},{"unicode":"U+144E3","char":"𔓣","name":"ANATOLIAN HIEROGLYPH A200","category":"ancient_scripts","block":"Anatolian Hieroglyphs","required_font_family":"NotoSansAnatolianHieroglyphs-Regular"},{"unicode":"U+144E4","char":"𔓤","name":"ANATOLIAN HIEROGLYPH A201","category":"ancient_scripts","block":"Anatolian Hieroglyphs","required_font_family":"NotoSansAnatolianHieroglyphs-Regular"},{"unicode":"U+144E5","char":"𔓥","name":"ANATOLIAN HIEROGLYPH A202","category":"ancient_scripts","block":"Anatolian Hieroglyphs","required_font_family":"NotoSansAnatolianHieroglyphs-Regular"},{"unicode":"U+144E6","char":"𔓦","name":"ANATOLIAN HIEROGLYPH A202A","category":"ancient_scripts","block":"Anatolian Hieroglyphs","required_font_family":"NotoSansAnatolianHieroglyphs-Regular"},{"unicode":"U+144E7","char":"𔓧","name":"ANATOLIAN HIEROGLYPH A202B","category":"ancient_scripts","block":"Anatolian Hieroglyphs","required_font_family":"NotoSansAnatolianHieroglyphs-Regular"},{"unicode":"U+144E8","char":"𔓨","name":"ANATOLIAN HIEROGLYPH A203","category":"ancient_scripts","block":"Anatolian Hieroglyphs","required_font_family":"NotoSansAnatolianHieroglyphs-Regular"},{"unicode":"U+144E9","char":"𔓩","name":"ANATOLIAN HIEROGLYPH A204","category":"ancient_scripts","block":"Anatolian Hieroglyphs","required_font_family":"NotoSansAnatolianHieroglyphs-Regular"},{"unicode":"U+144EA","char":"𔓪","name":"ANATOLIAN HIEROGLYPH A205","category":"ancient_scripts","block":"Anatolian Hieroglyphs","required_font_family":"NotoSansAnatolianHieroglyphs-Regular"},{"unicode":"U+144EB","char":"𔓫","name":"ANATOLIAN HIEROGLYPH A206","category":"ancient_scripts","block":"Anatolian Hieroglyphs","required_font_family":"NotoSansAnatolianHieroglyphs-Regular"},{"unicode":"U+144EC","char":"𔓬","name":"ANATOLIAN HIEROGLYPH A207","category":"ancient_scripts","block":"Anatolian Hieroglyphs","required_font_family":"NotoSansAnatolianHieroglyphs-Regular"},{"unicode":"U+144ED","char":"𔓭","name":"ANATOLIAN HIEROGLYPH A207A","category":"ancient_scripts","block":"Anatolian Hieroglyphs","required_font_family":"NotoSansAnatolianHieroglyphs-Regular"},{"unicode":"U+144EE","char":"𔓮","name":"ANATOLIAN HIEROGLYPH A208","category":"ancient_scripts","block":"Anatolian Hieroglyphs","required_font_family":"NotoSansAnatolianHieroglyphs-Regular"},{"unicode":"U+144EF","char":"𔓯","name":"ANATOLIAN HIEROGLYPH A209","category":"ancient_scripts","block":"Anatolian Hieroglyphs","required_font_family":"NotoSansAnatolianHieroglyphs-Regular"},{"unicode":"U+144F0","char":"𔓰","name":"ANATOLIAN HIEROGLYPH A209A","category":"ancient_scripts","block":"Anatolian Hieroglyphs","required_font_family":"NotoSansAnatolianHieroglyphs-Regular"},{"unicode":"U+144F1","char":"𔓱","name":"ANATOLIAN HIEROGLYPH A210","category":"ancient_scripts","block":"Anatolian Hieroglyphs","required_font_family":"NotoSansAnatolianHieroglyphs-Regular"}]