[{"unicode":"U+1F5E0","char":"🗠","name":"STOCK CHART","category":"miscellaneous","block":"Miscellaneous Symbols and Pictographs","required_font_family":""},{"unicode":"U+1F5E1","char":"🗡","name":"DAGGER KNIFE","category":"miscellaneous","block":"Miscellaneous Symbols and Pictographs","required_font_family":""},{"unicode":"U+1F5E2","char":"🗢","name":"LIPS","category":"miscellaneous","block":"Miscellaneous Symbols and Pictographs","required_font_family":""},{"unicode":"U+1F5E3","char":"🗣","name":"SPEAKING HEAD IN SILHOUETTE","category":"miscellaneous","block":"Miscellaneous Symbols and Pictographs","required_font_family":""},{"unicode":"U+1F5E4","char":"🗤","name":"THREE RAYS ABOVE","category":"miscellaneous","block":"Miscellaneous Symbols and Pictographs","required_font_family":""},{"unicode":"U+1F5E5","char":"🗥","name":"THREE RAYS BELOW","category":"miscellaneous","block":"Miscellaneous Symbols and Pictographs","required_font_family":""},{"unicode":"U+1F5E6","char":"🗦","name":"THREE RAYS LEFT","category":"miscellaneous","block":"Miscellaneous Symbols and Pictographs","required_font_family":""},{"unicode":"U+1F5E7","char":"🗧","name":"THREE RAYS RIGHT","category":"miscellaneous","block":"Miscellaneous Symbols and Pictographs","required_font_family":""},{"unicode":"U+1F5E8","char":"🗨","name":"LEFT SPEECH BUBBLE","category":"miscellaneous","block":"Miscellaneous Symbols and Pictographs","required_font_family":""},{"unicode":"U+1F5E9","char":"🗩","name":"RIGHT SPEECH BUBBLE","category":"miscellaneous","block":"Miscellaneous Symbols and Pictographs","required_font_family":""},{"unicode":"U+1F5EA","char":"🗪","name":"TWO SPEECH BUBBLES","category":"miscellaneous","block":"Miscellaneous Symbols and Pictographs","required_font_family":""},{"unicode":"U+1F5EB","char":"🗫","name":"THREE SPEECH BUBBLES","category":"miscellaneous","block":"Miscellaneous Symbols and Pictographs","required_font_family":""},{"unicode":"U+1F5EC","char":"🗬","name":"LEFT THOUGHT BUBBLE","category":"miscellaneous","block":"Miscellaneous Symbols and Pictographs","required_font_family":""},{"unicode":"U+1F5ED","char":"🗭","name":"RIGHT THOUGHT BUBBLE","category":"miscellaneous","block":"Miscellaneous Symbols and Pictographs","required_font_family":""},{"unicode":"U+1F5EE","char":"🗮","name":"LEFT ANGER BUBBLE","category":"miscellaneous","block":"Miscellaneous Symbols and Pictographs","required_font_family":""},{"unicode":"U+1F5EF","char":"🗯","name":"RIGHT ANGER BUBBLE","category":"miscellaneous","block":"Miscellaneous Symbols and Pictographs","required_font_family":""},{"unicode":"U+1F5F0","char":"🗰","name":"MOOD BUBBLE","category":"miscellaneous","block":"Miscellaneous Symbols and Pictographs","required_font_family":""},{"unicode":"U+1F5F1","char":"🗱","name":"LIGHTNING MOOD BUBBLE","category":"miscellaneous","block":"Miscellaneous Symbols and Pictographs","required_font_family":""},{"unicode":"U+1F5F2","char":"🗲","name":"LIGHTNING MOOD","category":"miscellaneous","block":"Miscellaneous Symbols and Pictographs","required_font_family":""},{"unicode":"U+1F5F3","char":"🗳","name":"BALLOT BOX WITH BALLOT","category":"miscellaneous","block":"Miscellaneous Symbols and Pictographs","required_font_family":""},{"unicode":"U+1F5F4","char":"🗴","name":"BALLOT SCRIPT X","category":"miscellaneous","block":"Miscellaneous Symbols and Pictographs","required_font_family":""},{"unicode":"U+1F5F5","char":"🗵","name":"BALLOT BOX WITH SCRIPT X","category":"miscellaneous","block":"Miscellaneous Symbols and Pictographs","required_font_family":""},{"unicode":"U+1F5F6","char":"🗶","name":"BALLOT BOLD SCRIPT X","category":"miscellaneous","block":"Miscellaneous Symbols and Pictographs","required_font_family":""},{"unicode":"U+1F5F7","char":"🗷","name":"BALLOT BOX WITH BOLD SCRIPT X","category":"miscellaneous","block":"Miscellaneous Symbols and Pictographs","required_font_family":""},{"unicode":"U+1F5F8","char":"🗸","name":"LIGHT CHECK MARK","category":"miscellaneous","block":"Miscellaneous Symbols and Pictographs","required_font_family":""},{"unicode":"U+1F5F9","char":"🗹","name":"BALLOT BOX WITH BOLD CHECK","category":"miscellaneous","block":"Miscellaneous Symbols and Pictographs","required_font_family":""},{"unicode":"U+1F5FA","char":"🗺","name":"WORLD MAP","category":"miscellaneous","block":"Miscellaneous Symbols and Pictographs","required_font_family":""},{"unicode":"U+1F5FB","char":"🗻","name":"MOUNT FUJI","category":"miscellaneous","block":"Miscellaneous Symbols and Pictographs","required_font_family":""},{"unicode":"U+1F5FC","char":"🗼","name":"TOKYO TOWER","category":"miscellaneous","block":"Miscellaneous Symbols and Pictographs","required_font_family":""},{"unicode":"U+1F5FD","char":"🗽","name":"STATUE OF LIBERTY","category":"miscellaneous","block":"Miscellaneous Symbols and Pictographs","required_font_family":""},{"unicode":"U+1F5FE","char":"🗾","name":"SILHOUETTE OF JAPAN","category":"miscellaneous","block":"Miscellaneous Symbols and Pictographs","required_font_family":""},{"unicode":"U+1F5FF","char":"🗿","name":"MOYAI","category":"miscellaneous","block":"Miscellaneous Symbols and Pictographs","required_font_family":""},{"unicode":"U+1F600","char":"😀","name":"GRINNING FACE","category":"dingbats","block":"Emoticons","required_font_family":""},{"unicode":"U+1F601","char":"😁","name":"GRINNING FACE WITH SMILING EYES","category":"dingbats","block":"Emoticons","required_font_family":""},{"unicode":"U+1F602","char":"😂","name":"FACE WITH TEARS OF JOY","category":"dingbats","block":"Emoticons","required_font_family":""},{"unicode":"U+1F603","char":"😃","name":"SMILING FACE WITH OPEN MOUTH","category":"dingbats","block":"Emoticons","required_font_family":""},{"unicode":"U+1F604","char":"😄","name":"SMILING FACE WITH OPEN MOUTH AND SMILING EYES","category":"dingbats","block":"Emoticons","required_font_family":""},{"unicode":"U+1F605","char":"😅","name":"SMILING FACE WITH OPEN MOUTH AND COLD SWEAT","category":"dingbats","block":"Emoticons","required_font_family":""},{"unicode":"U+1F606","char":"😆","name":"SMILING FACE WITH OPEN MOUTH AND TIGHTLY-CLOSED EYES","category":"dingbats","block":"Emoticons","required_font_family":""},{"unicode":"U+1F607","char":"😇","name":"SMILING FACE WITH HALO","category":"dingbats","block":"Emoticons","required_font_family":""},{"unicode":"U+1F608","char":"😈","name":"SMILING FACE WITH HORNS","category":"dingbats","block":"Emoticons","required_font_family":""},{"unicode":"U+1F609","char":"😉","name":"WINKING FACE","category":"dingbats","block":"Emoticons","required_font_family":""},{"unicode":"U+1F60A","char":"😊","name":"SMILING FACE WITH SMILING EYES","category":"dingbats","block":"Emoticons","required_font_family":""},{"unicode":"U+1F60B","char":"😋","name":"FACE SAVOURING DELICIOUS FOOD","category":"dingbats","block":"Emoticons","required_font_family":""},{"unicode":"U+1F60C","char":"😌","name":"RELIEVED FACE","category":"dingbats","block":"Emoticons","required_font_family":""},{"unicode":"U+1F60D","char":"😍","name":"SMILING FACE WITH HEART-SHAPED EYES","category":"dingbats","block":"Emoticons","required_font_family":""},{"unicode":"U+1F60E","char":"😎","name":"SMILING FACE WITH SUNGLASSES","category":"dingbats","block":"Emoticons","required_font_family":""},{"unicode":"U+1F60F","char":"😏","name":"SMIRKING FACE","category":"dingbats","block":"Emoticons","required_font_family":""},{"unicode":"U+1F610","char":"😐","name":"NEUTRAL FACE","category":"dingbats","block":"Emoticons","required_font_family":""},{"unicode":"U+1F611","char":"😑","name":"EXPRESSIONLESS FACE","category":"dingbats","block":"Emoticons","required_font_family":""},{"unicode":"U+1F612","char":"😒","name":"UNAMUSED FACE","category":"dingbats","block":"Emoticons","required_font_family":""},{"unicode":"U+1F613","char":"😓","name":"FACE WITH COLD SWEAT","category":"dingbats","block":"Emoticons","required_font_family":""},{"unicode":"U+1F614","char":"😔","name":"PENSIVE FACE","category":"dingbats","block":"Emoticons","required_font_family":""},{"unicode":"U+1F615","char":"😕","name":"CONFUSED FACE","category":"dingbats","block":"Emoticons","required_font_family":""},{"unicode":"U+1F616","char":"😖","name":"CONFOUNDED FACE","category":"dingbats","block":"Emoticons","required_font_family":""},{"unicode":"U+1F617","char":"😗","name":"KISSING FACE","category":"dingbats","block":"Emoticons","required_font_family":""},{"unicode":"U+1F618","char":"😘","name":"FACE THROWING A KISS","category":"dingbats","block":"Emoticons","required_font_family":""},{"unicode":"U+1F619","char":"😙","name":"KISSING FACE WITH SMILING EYES","category":"dingbats","block":"Emoticons","required_font_family":""},{"unicode":"U+1F61A","char":"😚","name":"KISSING FACE WITH CLOSED EYES","category":"dingbats","block":"Emoticons","required_font_family":""},{"unicode":"U+1F61B","char":"😛","name":"FACE WITH STUCK-OUT TONGUE","category":"dingbats","block":"Emoticons","required_font_family":""}]